.hgignore
MANIFEST.in
README.rst
greenlet-tests.txt
proxy-tests.txt
setup.cfg
setup.py
test_wsgi_lite.py
tests.txt
wsgi_bindings.py
wsgi_lite.py
wsgi_lite.egg-info/PKG-INFO
wsgi_lite.egg-info/SOURCES.txt
wsgi_lite.egg-info/dependency_links.txt
wsgi_lite.egg-info/top_level.txt