Metadata-Version: 1.0
Name: wsgi-lite
Version: 0.5a3-1
Summary: A better way to write WSGI apps and middleware
Home-page: https://bitbucket.org/pje/wsgi_lite/
Author: P.J. Eby
Author-email: web-sig@python.org
License: ASF
Download-URL: https://bitbucket.org/pje/wsgi_lite/get/default.tar.gz#egg=wsgi_lite-dev
Platform: UNKNOWN
